youtube_video_upload/__init__.py
youtube_video_upload/__main__.py
youtube_video_upload/auth.py
youtube_video_upload/get_category_number.py
youtube_video_upload/get_credentials.py
youtube_video_upload/support.py
youtube_video_upload/upload_from_options.py
youtube_video_upload/upload_video.py
youtube_video_upload-0.2.0.dist-info/METADATA
youtube_video_upload-0.2.0.dist-info/WHEEL
youtube_video_upload-0.2.0.dist-info/top_level.txt
youtube_video_upload-0.2.0.dist-info/RECORD
