Metadata-Version: 2.1
Name: youtube-video-upload
Version: 0.2.0
Summary: Youtube video uploader
Home-page: https://github.com/remorses/youtube-video-upload
Author: Tommaso De Rossi
Author-email: beats.by.morse@gmail.com
License: MIT
Platform: UNKNOWN
Requires-Dist: pyyaml
Requires-Dist: colorama
Requires-Dist: google-api-python-client
Requires-Dist: requests
Requires-Dist: google-auth
Requires-Dist: google-auth-oauthlib
Requires-Dist: google-auth-httplib2
Requires-Dist: oauth2client
